amy/__init__.py
amy/actions.py
amy/env.py
amy/instance.py
amy/message.py
amy/plugin.py
amy-3.4.0.dist-info/METADATA
amy-3.4.0.dist-info/WHEEL
amy-3.4.0.dist-info/top_level.txt
amy-3.4.0.dist-info/RECORD
