Metadata-Version: 2.1
Name: amy
Version: 3.4.0
Summary: A module to write amy plugins
Home-page: https://gitlab.com/amy-assistant/plugins/python
Author: Liam Perlaki
Author-email: lperlaki@icloud.com
License: MIT
Platform: UNKNOWN
Classifier: License :: OSI Approved :: MIT License
Classifier: Programming Language :: Python :: 3
Classifier: Programming Language :: Python :: 3.7
Requires-Dist: kombu
Requires-Dist: cryptography
